dotbots/__init__.py
dotbots/controller.py
dotbots/hdlc.py
dotbots/joystick.py
dotbots/keyboard.py
dotbots/lighthouse2.py
dotbots/main.py
dotbots/models.py
dotbots/protocol.py
dotbots/serial_interface.py
dotbots/server.py
dotbots/frontend/.env
dotbots/frontend/.env.test
dotbots/frontend/.gitignore
dotbots/frontend/package-lock.json
dotbots/frontend/package.json
dotbots/frontend/build/asset-manifest.json
dotbots/frontend/build/index.html
dotbots/frontend/build/manifest.json
dotbots/frontend/build/robots.txt
dotbots/frontend/build/static/css/main.ab17a09a.css
dotbots/frontend/build/static/css/main.ab17a09a.css.map
dotbots/frontend/build/static/js/main.448389a5.js
dotbots/frontend/build/static/js/main.448389a5.js.LICENSE.txt
dotbots/frontend/build/static/js/main.448389a5.js.map
dotbots/frontend/build/static/media/bootstrap-icons.e559bf06bc84fd9525e6.woff
dotbots/frontend/build/static/media/bootstrap-icons.ea98e12d2d58747f9fc5.woff2
dotbots/frontend/coverage/coverage-final.json
dotbots/frontend/coverage/lcov.info
dotbots/frontend/coverage/lcov-report/DotBots.js.html
dotbots/frontend/coverage/lcov-report/DotBotsMap.js.html
dotbots/frontend/coverage/lcov-report/Joystick.js.html
dotbots/frontend/coverage/lcov-report/base.css
dotbots/frontend/coverage/lcov-report/block-navigation.js
dotbots/frontend/coverage/lcov-report/favicon.png
dotbots/frontend/coverage/lcov-report/index.html
dotbots/frontend/coverage/lcov-report/index.js.html
dotbots/frontend/coverage/lcov-report/prettify.css
dotbots/frontend/coverage/lcov-report/prettify.js
dotbots/frontend/coverage/lcov-report/rest.js.html
dotbots/frontend/coverage/lcov-report/sort-arrow-sprite.png
dotbots/frontend/coverage/lcov-report/sorter.js
dotbots/frontend/public/index.html
dotbots/frontend/public/manifest.json
dotbots/frontend/public/robots.txt
dotbots/frontend/src/DotBots.js
dotbots/frontend/src/DotBots.test.js
dotbots/frontend/src/DotBotsMap.js
dotbots/frontend/src/Joystick.js
dotbots/frontend/src/Joystick.test.js
dotbots-0.7.0.dist-info/METADATA
dotbots-0.7.0.dist-info/WHEEL
dotbots-0.7.0.dist-info/entry_points.txt
dotbots-0.7.0.dist-info/licenses/LICENSE.txt
dotbots-0.7.0.dist-info/RECORD
