Metadata-Version: 2.1
Name: dotbots
Version: 0.7.0
Summary: Package to easily control your DotBots and SailBots.
Project-URL: Homepage, https://github.com/DotBots/BotController-python
Project-URL: Bug Tracker, https://github.com/DotBots/BotController-python/issues
Author-email: Alexandre Abadie <alexandre.abadie@inria.fr>, Theo Akbas <theo.akbas@inria.fr>
License: MIT
License-File: LICENSE.txt
Classifier: License :: OSI Approved :: MIT License
Classifier: Operating System :: OS Independent
Classifier: Programming Language :: Python :: 3
Requires-Python: >=3.7
Requires-Dist: click==8.1.3
Requires-Dist: fastapi==0.85.1
Requires-Dist: numpy==1.23.4
Requires-Dist: opencv-python==4.6.0.66
Requires-Dist: pygame==2.1.2
Requires-Dist: pynput==1.7.6
Requires-Dist: pyserial==3.5
Requires-Dist: rich==12.6.0
Requires-Dist: uvicorn==0.18.3
Requires-Dist: websockets==10.4
